README.txt
setup.py
LCConnect/LCConnect.py
LCConnect/__init__.py
LCConnect.egg-info/PKG-INFO
LCConnect.egg-info/SOURCES.txt
LCConnect.egg-info/dependency_links.txt
LCConnect.egg-info/requires.txt
LCConnect.egg-info/top_level.txt