Metadata-Version: 1.0
Name: LCConnect
Version: 0.1
Summary: Lending Club API made to a lib
Home-page: https://www.test.com
Author: EranArtzi
Author-email: eartzi@gmail.com
License: UNKNOWN
Platform: UNKNOWN
